setup.cfg
setup.py
ext/src/_neuroglancer.cc
ext/src/mesh_objects.cc
ext/src/on_demand_object_mesh_generator.cc
ext/src/openmesh_dependencies.cc
ext/src/voxel_mesh_generator.cc
glancer.egg-info/PKG-INFO
glancer.egg-info/SOURCES.txt
glancer.egg-info/dependency_links.txt
glancer.egg-info/requires.txt
glancer.egg-info/top_level.txt
neuroglancer/__init__.py
neuroglancer/base_viewer.py
neuroglancer/chunks.py
neuroglancer/downsample.py
neuroglancer/downsample_scales.py
neuroglancer/graph_server.py
neuroglancer/graph_test.py
neuroglancer/randomtoken.py
neuroglancer/server.py
neuroglancer/viewer.py
neuroglancer/volume.py
neuroglancer/static/__init__.py
neuroglancer/static/index.html