Metadata-Version: 1.0
Name: glancer
Version: 0.0.6
Summary: Python data backend for neuroglancer, a WebGL-based viewer for volumetric data
Home-page: https://github.com/seunglab/neuroglancer
Author: Jeremy Maitin-Shepard, Jan Funke, Ignacio Tartavull
Author-email: jbms@google.com, jfunke@iri.upc.edu, tartavull@gmail.com
License: Apache License 2.0
Platform: UNKNOWN
